wokcounty/__init__.py
wokcounty/aes.py
wokcounty-0.0.1.dist-info/licenses/LICENSE
wokcounty-0.0.1.dist-info/METADATA
wokcounty-0.0.1.dist-info/WHEEL
wokcounty-0.0.1.dist-info/top_level.txt
wokcounty-0.0.1.dist-info/RECORD
