Metadata-Version: 2.4
Name: wokcounty
Version: 0.0.1
Summary: The only correct, pure, PEP 8 compliant implementation of AES-128 which do not use modes of operation, iv etc but follows the core AES-128 standard only (Details: others are either incorrect as given the same input as that specified in AES-128, it produce a different output and hence by AES-128 is deemed not compliant; or they use iv, modes of operations like CBC/ECB, padding, salt, password-based key deriviation, randomness et cetera).
Author-email: Gan Shao Wen <shaowen095@gmail.com>
License-Expression: MIT
Project-URL: Homepage, https://github.com/NK5W/security
Project-URL: Issues, https://github.com/NK5W/security/issues
Keywords: AES_128,AES-128,AES 128,AES,128,advanced encryption standard,advanced,encryption,standard,Rijndael,encryption,decryption,security,privacy,cryptography,password,passwords,encrypt,decrypt,bitlocker,secure,file,data,protection,lite,small,basic,simple,strong,protected,safety,safe,vault,pep 8,pep,8,python enhancement proposal,python,enhancement,proposal,advanced_encryption_standard,pep_8,cipher,block,block cipher,block_cipher,block-cipher,advanced-encryption-standard,android,windows,tiny
Classifier: Programming Language :: Python
Classifier: Programming Language :: Python :: 3
Classifier: Programming Language :: Python :: 3.13
Classifier: Programming Language :: Python :: Implementation :: CPython
Classifier: Operating System :: OS Independent
Classifier: Topic :: Security :: Cryptography
Classifier: Topic :: Security
Classifier: Topic :: Utilities
Classifier: Topic :: Communications
Classifier: Topic :: Internet
Classifier: Topic :: Multimedia
Classifier: Topic :: Terminals
Classifier: Topic :: Text Processing
Classifier: Topic :: Text Processing :: General
Classifier: Topic :: Text Processing :: Indexing
Classifier: Topic :: Text Processing :: Linguistic
Classifier: Topic :: Text Processing :: Markup
Classifier: Topic :: Text Processing :: Markup :: HTML
Classifier: Topic :: Text Processing :: Markup :: LaTeX
Classifier: Topic :: Text Processing :: Markup :: Markdown
Classifier: Topic :: Text Processing :: Markup :: reStructuredText
Requires-Python: <3.14,>=3.9
License-File: LICENSE
Dynamic: license-file
